pygnuregex/__init__.py
pygnuregex/stub.so
pygnuregex-1.1.5.dist-info/METADATA
pygnuregex-1.1.5.dist-info/WHEEL
pygnuregex-1.1.5.dist-info/top_level.txt
pygnuregex-1.1.5.dist-info/RECORD
pygnuregex-1.1.5.dist-info/licenses/COPYING
