Metadata-Version: 2.4
Name: pygnuregex
Version: 1.1.5
Summary: An implementation of the GNU interface to regex in Python
Author-email: Nikolaos Chatzikonstantinou <nchatz314@gmail.com>
License-Expression: GPL-3.0-or-later
Project-URL: Homepage, https://codeberg.org/annoyingusername/pygnuregex/
Project-URL: Issues, https://codeberg.org/annoyingusername/pygnuregex/issues
Classifier: Programming Language :: Python :: 3
Classifier: Operating System :: OS Independent
Requires-Python: >=3.8
License-File: COPYING
Provides-Extra: tests
Requires-Dist: pytest; extra == "tests"
Dynamic: license-file
